sqlgpt_parser/__init__.py
sqlgpt_parser/format/__init__.py
sqlgpt_parser/format/formatter.py
sqlgpt_parser/parser/__init__.py
sqlgpt_parser/parser/exceptions.py
sqlgpt_parser/parser/parser_utils.py
sqlgpt_parser/parser/mysql_parser/__init__.py
sqlgpt_parser/parser/mysql_parser/lexer.py
sqlgpt_parser/parser/mysql_parser/parser.py
sqlgpt_parser/parser/mysql_parser/parser_table.py
sqlgpt_parser/parser/mysql_parser/reserved.py
sqlgpt_parser/parser/oceanbase_parser/__init__.py
sqlgpt_parser/parser/oceanbase_parser/lexer.py
sqlgpt_parser/parser/oceanbase_parser/parser.py
sqlgpt_parser/parser/oceanbase_parser/parser_table.py
sqlgpt_parser/parser/oceanbase_parser/reserved.py
sqlgpt_parser/parser/odps_parser/__init__.py
sqlgpt_parser/parser/odps_parser/lexer.py
sqlgpt_parser/parser/odps_parser/parser.py
sqlgpt_parser/parser/odps_parser/parser_table.py
sqlgpt_parser/parser/odps_parser/reserved.py
sqlgpt_parser/parser/tree/__init__.py
sqlgpt_parser/parser/tree/approximate.py
sqlgpt_parser/parser/tree/call_argument.py
sqlgpt_parser/parser/tree/explain.py
sqlgpt_parser/parser/tree/expression.py
sqlgpt_parser/parser/tree/field_type.py
sqlgpt_parser/parser/tree/grouping.py
sqlgpt_parser/parser/tree/index_type.py
sqlgpt_parser/parser/tree/join_criteria.py
sqlgpt_parser/parser/tree/literal.py
sqlgpt_parser/parser/tree/node.py
sqlgpt_parser/parser/tree/qualified_name.py
sqlgpt_parser/parser/tree/query_specification.py
sqlgpt_parser/parser/tree/relation.py
sqlgpt_parser/parser/tree/rewrite.py
sqlgpt_parser/parser/tree/select.py
sqlgpt_parser/parser/tree/select_item.py
sqlgpt_parser/parser/tree/set_operation.py
sqlgpt_parser/parser/tree/sort_item.py
sqlgpt_parser/parser/tree/statement.py
sqlgpt_parser/parser/tree/table.py
sqlgpt_parser/parser/tree/table_element.py
sqlgpt_parser/parser/tree/transaction.py
sqlgpt_parser/parser/tree/values.py
sqlgpt_parser/parser/tree/visitor.py
sqlgpt_parser/parser/tree/window.py
sqlgpt_parser/parser/tree/with_stmt.py
sqlgpt_parser-0.0.1a5.dist-info/WHEEL
sqlgpt_parser-0.0.1a5.dist-info/METADATA
sqlgpt_parser-0.0.1a5.dist-info/RECORD
