Metadata-Version: 2.1
Name: sqlgpt-parser
Version: 0.0.1a5
Summary: A sql parser which support mysql, oceanbase and odps
Author-email: luliwjc <chenxiaoxi_wjc@163.com>, Ifffff <tingkai.ztk@antgroup.com>, tomato <1083369179@qq.com>
Requires-Python: >=3.7
Classifier: Programming Language :: Python :: 3
Classifier: License :: OSI Approved :: Apache Software License
Classifier: Operating System :: OS Independent
Requires-Dist: ply == 3.11
Project-URL: Bug Tracker, https://github.com/eosphoros-ai/sqlgpt-parser/issues
Project-URL: Homepage, https://github.com/eosphoros-ai/sqlgpt-parser
